myhellopackage/__init__.py
myhellopackage/channel.py
myhellopackage/hello.py
helloPypi_topic-0.0.7.dist-info/METADATA
helloPypi_topic-0.0.7.dist-info/WHEEL
helloPypi_topic-0.0.7.dist-info/top_level.txt
helloPypi_topic-0.0.7.dist-info/RECORD
