Metadata-Version: 2.1
Name: helloPypi-topic
Version: 0.0.7
Summary: A basic hello package
Author: Caleb
